mini_pickle_db/__init__.py
mini_pickle_db/pickle_db.py
mini_pickle_db-0.1.0.dist-info/LICENSE
mini_pickle_db-0.1.0.dist-info/METADATA
mini_pickle_db-0.1.0.dist-info/WHEEL
mini_pickle_db-0.1.0.dist-info/top_level.txt
mini_pickle_db-0.1.0.dist-info/RECORD
