Metadata-Version: 2.1
Name: mini-pickle-db
Version: 0.1.0
Summary: Mini pickle database
Home-page: https://github.com/murrou-cell/mini_pickle_db
Author: Marin Dragolov
Author-email: murrou13@gmail.com
Project-URL: Bug Tracker, https://github.com/murrou-cell/mini_pickle_db/issues
Classifier: Programming Language :: Python :: 3
Classifier: License :: OSI Approved :: MIT License
Classifier: Operating System :: OS Independent
Requires-Python: >=3.6
License-File: LICENSE
